pretix_esncard/__init__.py
pretix_esncard/api.py
pretix_esncard/apps.py
pretix_esncard/forms.py
pretix_esncard/helpers.py
pretix_esncard/models.py
pretix_esncard/signals.py
pretix_esncard/temp.py
pretix_esncard/test_data.py
pretix_esncard-1.2.0.dist-info/licenses/LICENSE
pretix_esncard-1.2.0.dist-info/METADATA
pretix_esncard-1.2.0.dist-info/WHEEL
pretix_esncard-1.2.0.dist-info/entry_points.txt
pretix_esncard-1.2.0.dist-info/top_level.txt
pretix_esncard-1.2.0.dist-info/RECORD
