Metadata-Version: 2.4
Name: pretix-esncard
Version: 1.2.0
Summary: A plugin for pretix allowing automated validation of ESNcard numbers
Author-email: Mårten Lundström <marten.lundstrom@esnsweden.org>, Elias Jollivet <wpa@esnsweden.org>
Maintainer-email: Elias Jollivet <wpa@esnsweden.org>
License-Expression: Apache-2.0
Project-URL: homepage, https://github.com/esn-sweden/pretix-esncard
Project-URL: repository, https://github.com/esn-sweden/pretix-esncard
Keywords: pretix,esncard,esn,plugin,validation
Requires-Python: >=3.10
License-File: LICENSE
Requires-Dist: requests<3,>=2.32
Requires-Dist: pydantic<3,>=2.12
Dynamic: license-file
